static_folders/__init__.py
static_folders/folder.py
static_folders/folder_interface.py
static_folders/partitioned_folder.py
static_folders/py.typed
static_folders-0.3.0.dist-info/METADATA
static_folders-0.3.0.dist-info/WHEEL
static_folders-0.3.0.dist-info/licenses/LICENSE
static_folders-0.3.0.dist-info/RECORD
