Metadata-Version: 2.4
Name: static-folders
Version: 0.3.0
Summary: Modelling Static folder structures for python applications
Author-email: Matt Richards <mrichards7@outlook.com.au>
License-File: LICENSE
Requires-Python: >=3.7
Requires-Dist: attrs>=24.2.0
Requires-Dist: typing-extensions>=4.14.0; python_version >= '3.13'
Requires-Dist: typing-extensions>=4.7.1; python_version < '3.13'
